{"  INKSTER": 0, "  LINCOLN PARK": 1, "  OAK PARK": 2, "  PONTIAC": 3, "  SOUTHFIELD": 4, " CLINTONTOWNSHIP": 5, " DETROIT": 6, "ADRIAN": 7, "ALEXANDRIA": 8, "ALGONAC": 9, "ATTICA": 10, "AUBURN HILLS": 11, "BEDFORD": 12, "BELLEVILLE": 13, "BERKLEY": 14, "BEVERLY HILLS": 15, "BIRMINGHAM": 16, "BIRMNIGHAM": 17, "BLOOMFIELD  HILLS": 18, "BLOOMFIELD HILLS": 19, "BRIGHTON": 20, "BROWNSTOWN": 21, "BROWNSTOWN TWP": 22, "BURTON": 23, "CANTON": 24, "CARO": 25, "CENTER LINE": 26, "CENTERLINE": 27, "CHATTANOOGA": 28, "CHESTERFIELD": 29, "CHULA VISTA": 30, "CLARKSTON": 31, "CLAWSON": 32, "CLAY": 33, "CLINTON TOWNSHIP": 34, "CLINTON TWP": 35, "CLINTONTOWNSHIP": 36, "COMMERCE CHARTER TOWNSHIP": 37, "COMMERCE TOWNSHIP": 38, "COTTRELLVILLE": 39, "Casco": 40, "Clinton Township": 41, "Columbus": 42, "DEARBORN": 43, "DEARBORN HEIGHTS": 44, "DETEROIT": 45, "DETOIT": 46, "DETROIIT": 47, "DETROIT": 48, "DETROT": 49, "Detroit": 50, "EAST POINTE": 51, "EASTPOINT": 52, "EASTPOINTE": 53, "ECORSE": 54, "East Pointe": 55, "Eastpointe": 56, "FARMINGTON": 57, "FARMINGTON HILL": 58, "FARMINGTON HILLS": 59, "FARMNIGTON HILLS": 60, "FERNDALE": 61, "FLINT": 62, "FRANKLIN": 63, "FRASER": 64, "Farmington": 65, "Farmington Hills": 66, "Ferndale": 67, "Fraser": 68, "GARDEN CITY": 69, "GREENVILLE": 70, "GROOSE POINT WOODS": 71, "GROSSE POINT WOODS": 72, "GROSSE POINTE": 73, "GROSSE POINTE PARK": 74, "GROSSE POINTE WOODS": 75, "Gardena": 76, "HALZEL PARK": 77, "HAMTRACK": 78, "HAMTRAMACK": 79, "HAMTRAMCK": 80, "HAPER WOODS": 81, "HARPER WOODS": 82, "HARRISON  TWP": 83, "HARRISON TONWSHIP": 84, "HARRISON TOWNSHIP": 85, "HARRISON TWP": 86, "HARTLAND": 87, "HAZEL PAK": 88, "HAZEL PARK": 89, "HAZEL PARK,": 90, "HAZELPARK": 91, "HIGHLAND PARK": 92, "HOLLY": 93, "HUNINGTON WOODS": 94, "HUNTINGTON WOODS": 95, "Hamtramck": 96, "Harper Woods": 97, "Harrison Township": 98, "Highalnd Park": 99, "Highland Park": 100, "INKSTER": 101, "JACKSON": 102, "KALKASKA": 103, "KEEGO HARBOR": 104, "LAKE ORION": 105, "LANSING": 106, "LAPEER": 107, "LATHRUP VILLAGE": 108, "LEONARD": 109, "LINCOLN PARK": 110, "LINDEN": 111, "LIVONIA": 112, "LOUISVILLE": 113, "Lincoln Park": 114, "MACOMB": 115, "MADISION HEIGHTS": 116, "MADISON  HEIGHTS": 117, "MADISON HEIGHT": 118, "MADISON HEIGHTS": 119, "MADISON HGTS": 120, "MADISON HTS": 121, "MELVINDALE": 122, "MILFORD": 123, "MOUNT CLEMENS": 124, "MOUNT CLEMONS": 125, "MT CLEMENS": 126, "Madison Heights": 127, "Melvindale": 128, "N CAROLINA": 129, "NEW BALTIMORE": 130, "NORTHVILLE": 131, "NOVI": 132, "OAK PARK": 133, "OWOSSO": 134, "OXFORD": 135, "Oak Park": 136, "Oakpark": 137, "PLANO": 138, "PLEASANT RIDGE": 139, "PLYMOUTH": 140, "PONTIAC": 141, "PORT HURON": 142, "PRESCOTT": 143, "Pleasant Ridge": 144, "Pontiac": 145, "RAY TOWNSHIP": 146, "REDFORD": 147, "REDFORD CHARTER TWP": 148, "REDFORD TOWNSHIP": 149, "REDFORD, TOWNSHIP": 150, "RIVER ROUGE": 151, "ROCHESTER": 152, "ROCHESTER  HILL": 153, "ROCHESTER HILLS": 154, "ROMULUS": 155, "ROSEVILLA": 156, "ROSEVILLE": 157, "ROYAL OAK": 158, "Redford": 159, "Roseville": 160, "Royal Oak": 161, "SAINT CLAIR SHORES": 162, "SAINT CLAIRE SHORES": 163, "SAINT PAUL": 164, "SANDUSKY": 165, "SHEBLEY TOWNSHIP": 166, "SHEBLY TOWNSHIP": 167, "SHELBY TOWNSHIP": 168, "SHELBY TWP": 169, "SOUTH ROCKWOOD": 170, "SOUTHFIELD": 171, "SOUTHGATE": 172, "SOUUTHFIELD": 173, "ST CLAIR SHORES": 174, "ST CLAIRSHORE": 175, "ST. CLAIR SHORES": 176, "STERLING  HEIGHTS": 177, "STERLING HEIGHT": 178, "STERLING HEIGHTS": 179, "STERLING HTS": 180, "STOUGHTON": 181, "Saint Clair Shores": 182, "Shelby Township": 183, "Southfield": 184, "St Clair Shores": 185, "Sterling Heights": 186, "TAYLOR": 187, "TROY": 188, "Trenton": 189, "Troy": 190, "VAN BUREN TWP": 191, "W BLOOMFIELD": 192, "WALLED LAKE": 193, "WARREN": 194, "WASHINGTON": 195, "WATERFORD": 196, "WAYNE": 197, "WEST  BLOOMFIELD": 198, "WEST BLOOMFIELD": 199, "WESTLAND": 200, "WIXOM": 201, "WOODHAVEN": 202, "WYANDOTTE": 203, "Warren": 204, "West  Bloomfield": 205, "West Bloomfield": 206, "Westland": 207, "YPSILANTI": 208}